Workbook

Sheet Assumptions
A1: Assumptions | B1: Base Case | C1: Bull Case | D1: Bear Case | F1: Active
A2: Company Name | B2: Blue Co Digital | E2: Scenario (1=Base, 2=Bull, 3=Bear): | F2: 1
A3: Currency | B3: USD (in millions) | E3: Actvie Scenario | F3: =IF(F2=1,"Base Case",IF(F2=2,"Bull Case",IF(F2=3,"Bear Case","Invalid"))) -> Base Case
A5: Revenue Assumptions
A6: Base Year Revenue | B6: 1000 | F6: =IF($F$2=1,B6,B6) -> 1000
A7: Revenue Growth Rate | B7: 0.1 | C7: 0.15 | D7: 0.05 | F7: =IF($F$2=1,B7,IF($F$2=2,C7,D7)) -> 0.1
A9: Cost Assumptions
A10: COGS (% of Revenue) | B10: 0.6 | C10: 0.55 | D10: 0.65 | F10: =IF($F$2=1,B10,IF($F$2=2,C10,D10)) -> 0.6
A11: Operating Expenses (% of Revenue) | B11: 0.2 | C11: 0.18 | D11: 0.23 | F11: =IF($F$2=1,B11,IF($F$2=2,C11,D11)) -> 0.2
A12: Tax Rate | B12: 0.25 | F12: =IF($F$2=1,B12,B12) -> 0.25
A14: Valuation Assumptions
A15: Discount Rate (WACC) | B15: 0.1 | C15: 0.08 | D15: 0.12 | F15: =IF($F$2=1,B15,IF($F$2=2,C15,D15)) -> 0.1
A16: Terminal Growth Rate | B16: 0.03 | C16: 0.04 | D16: 0.02 | F16: =IF($F$2=1,B16,IF($F$2=2,C16,D16)) -> 0.03
A17: Projection Years | B17: 5
A19: Balance Sheet Assumptions
A20: Starting Cash | B20: 100
A21: Accounts Receivable (% of Revenue) | B21: 0.08
A22: Inventory (% of COGS) | B22: 0.15
A23: Accounts Payable (% of COGS) | B23: 0.08
A24: Starting PP&E | B24: 500
A25: Annual Capital Exependiture | B25: 50
A26: Annual Depreciation | B26: 40
A27: Starting Short-Term Debt | B27: 50
A28: Starting Long-Term Debt | B28: 200

Sheet Income Statement
A1: Income Statement | B1: Year 1 | C1: Year 2 | D1: Year 3 | E1: Year 4 | F1: Year 5
A3: Revenue | B3: =Assumptions!$B$6*(1+Assumptions!$F$7) -> 1100 | C3: =B3*(1+Assumptions!$F$7) -> 1210 | D3: =C3*(1+Assumptions!$F$7) -> 1331 | E3: =D3*(1+Assumptions!$F$7) -> 1464.1 | F3: =E3*(1+Assumptions!$B$7) -> 1610.51
A4: COGS | B4: =B3*Assumptions!$F$10 -> 660 | C4: =C3*Assumptions!$F$10 -> 726 | D4: =D3*Assumptions!$F$10 -> 798.6 | E4: =E3*Assumptions!$F$10 -> 878.46 | F4: =F3*Assumptions!$B$10 -> 966.306
A5: Gross Profit | B5: =B3-B4 -> 440 | C5: =C3-C4 -> 484 | D5: =D3-D4 -> 532.4 | E5: =E3-E4 -> 585.64 | F5: =F3-F4 -> 644.204
A7: Operating Expenses | B7: =B3*Assumptions!$F$11 -> 220 | C7: =C3*Assumptions!$F$11 -> 242 | D7: =D3*Assumptions!$F$11 -> 266.2 | E7: =E3*Assumptions!$F$11 -> 292.82 | F7: =F3*Assumptions!$B$11 -> 322.102
A8: Operating Income | B8: =B5-B7 -> 220 | C8: =C5-C7 -> 242 | D8: =D5-D7 -> 266.2 | E8: =E5-E7 -> 292.82 | F8: =F5-F7 -> 322.102
A10: Interest Expense | B10: 0 | C10: 0 | D10: 0 | E10: 0 | F10: 0
A11: Pre-Tax Income | B11: =B8-B10 -> 220 | C11: =C8-C10 -> 242 | D11: =D8-D10 -> 266.2 | E11: =E8-E10 -> 292.82 | F11: =F8-F10 -> 322.102
A13: Taxes | B13: =B11*Assumptions!$F$12 -> 55 | C13: =C11*Assumptions!$F$12 -> 60.5 | D13: =D11*Assumptions!$F$12 -> 66.55 | E13: =E11*Assumptions!$F$12 -> 73.205 | F13: =F11*Assumptions!$B$12 -> 80.5255
A14: Net Income | B14: =B11-B13 -> 165 | C14: =C11-C13 -> 181.5 | D14: =D11-D13 -> 199.65 | E14: =E11-E13 -> 219.615 | F14: =F11-F13 -> 241.5765

Sheet Balance Sheet
A1: Balance Sheet | B1: Year 0 | C1: Year 1 | D1: Year 2 | E1: Year 3 | F1: Year 4 | G1: Year 5
A3: ASSETS
A4: Cash | B4: =Assumptions!B20 -> 100 | C4: =B4+'Income Statement'!B14+Assumptions!$B$26-Assumptions!$B$25-(C5-B5)-(C6-B6)+(C16-B16) -> 120.8 | D4: =C4+'Income Statement'!C14+Assumptions!$B$26-Assumptions!$B$25-(D5-C5)-(D6-C6)+(D16-C16) -> 278.88 | E4: =D4+'Income Statement'!D14+Assumptions!$B$26-Assumptions!$B$25-(E5-D5)-(E6-D6)+(E16-D16) -> 453.768 | F4: =E4+'Income Statement'!E14+Assumptions!$B$26-Assumptions!$B$25-(F5-E5)-(F6-E6)+(F16-E16) -> 647.1448 | G4: =F4+'Income Statement'!F14+Assumptions!$B$26-Assumptions!$B$25-(G5-F5)-(G6-F6)+(G16-F16) -> 860.85928
A5: Accounts Receivable | B5: 0 | C5: ='Income Statement'!B3*Assumptions!$B$21 -> 88 | D5: ='Income Statement'!C3*Assumptions!$B$21 -> 96.8 | E5: ='Income Statement'!D3*Assumptions!$B$21 -> 106.48 | F5: ='Income Statement'!E3*Assumptions!$B$21 -> 117.128 | G5: ='Income Statement'!F3*Assumptions!$B$21 -> 128.8408
A6: Inventory | B6: 0 | C6: ='Income Statement'!B4*Assumptions!$B$22 -> 99 | D6: ='Income Statement'!C4*Assumptions!$B$22 -> 108.9 | E6: ='Income Statement'!D4*Assumptions!$B$22 -> 119.79 | F6: ='Income Statement'!E4*Assumptions!$B$22 -> 131.769 | G6: ='Income Statement'!F4*Assumptions!$B$22 -> 144.9459
A7: Total Current Assets | B7: =B4+B5+B6 -> 100 | C7: =C4+C5+C6 -> 307.8 | D7: =D4+D5+D6 -> 484.58 | E7: =E4+E5+E6 -> 680.038 | F7: =F4+F5+F6 -> 896.0418 | G7: =G4+G5+G6 -> 1134.646
A9: Property, Plant & Equipment | B9: =Assumptions!B24 -> 500 | C9: =B9+Assumptions!$B$25 -> 550 | D9: =C9+Assumptions!$B$25 -> 600 | E9: =D9+Assumptions!$B$25 -> 650 | F9: =E9+Assumptions!$B$25 -> 700 | G9: =F9+Assumptions!$B$25 -> 750
A10: Less: Accumulated Depreciation | B10: 0 | C10: =B10+Assumptions!$B$26 -> 40 | D10: =C10+Assumptions!$B$26 -> 80 | E10: =D10+Assumptions!$B$26 -> 120 | F10: =E10+Assumptions!$B$26 -> 160 | G10: =F10+Assumptions!$B$26 -> 200
A11: Net PP&E | B11: =B9-B10 -> 500 | C11: =C9-C10 -> 510 | D11: =D9-D10 -> 520 | E11: =E9-E10 -> 530 | F11: =F9-F10 -> 540 | G11: =G9-G10 -> 550
A13: TOTAL ASSETS | B13: =B7+B11 -> 600 | C13: =C7+C11 -> 817.8 | D13: =D7+D11 -> 1004.58 | E13: =E7+E11 -> 1210.038 | F13: =F7+F11 -> 1436.0418 | G13: =G7+G11 -> 1684.646
A15: LIABILITIES
A16: Accounts Payable | B16: 0 | C16: ='Income Statement'!B4*Assumptions!$B$23 -> 52.8 | D16: ='Income Statement'!C4*Assumptions!$B$23 -> 58.08 | E16: ='Income Statement'!D4*Assumptions!$B$23 -> 63.888 | F16: ='Income Statement'!E4*Assumptions!$B$23 -> 70.2768 | G16: ='Income Statement'!F4*Assumptions!$B$23 -> 77.30448
A17: Short-Term Debt | B17: =Assumptions!B27 -> 50 | C17: =B17 -> 50 | D17: =C17 -> 50 | E17: =D17 -> 50 | F17: =E17 -> 50 | G17: =F17 -> 50
A18: Total Current Liabilities | B18: =B16+B17 -> 50 | C18: =C16+C17 -> 102.8 | D18: =D16+D17 -> 108.08 | E18: =E16+E17 -> 113.888 | F18: =F16+F17 -> 120.2768 | G18: =G16+G17 -> 127.30448
A20: Long-Term Debt | B20: =Assumptions!B28 -> 200 | C20: =B20 -> 200 | D20: =C20 -> 200 | E20: =D20 -> 200 | F20: =E20 -> 200 | G20: =F20 -> 200
A21: Total Liabilities | B21: =B18+B20 -> 250 | C21: =C18+C20 -> 302.8 | D21: =D18+D20 -> 308.08 | E21: =E18+E20 -> 313.888 | F21: =F18+F20 -> 320.2768 | G21: =G18+G20 -> 327.30448
A23: EQUITY
A24: Retained Earnings | B24: =B13-B21 -> 350 | C24: =B24+'Income Statement'!B14 -> 515 | D24: =C24+'Income Statement'!C14 -> 696.5 | E24: =D24+'Income Statement'!D14 -> 896.15 | F24: =E24+'Income Statement'!E14 -> 1115.765 | G24: =F24+'Income Statement'!F14 -> 1357.3415
A25: Total Equity | B25: =B24 -> 350 | C25: =C24 -> 515 | D25: =D24 -> 696.5 | E25: =E24 -> 896.15 | F25: =F24 -> 1115.765 | G25: =G24 -> 1357.3415
A27: TOTAL LIABILITIES & EQUITY | B27: =B21+B25 -> 600 | C27: =C21+C25 -> 817.8 | D27: =D21+D25 -> 1004.58 | E27: =E21+E25 -> 1210.038 | F27: =F21+F25 -> 1436.0418 | G27: =G21+G25 -> 1684.646
A29: Cash = Previous cash + Net Income - Capex
A30: AR = Revenue × AR% (from Assumptions)
A31: Inventory = COGS × Inventory% (from Assumptions)
A32: PP&E = Previous + Capex
A33: Accum Depr = Previous + Depreciation
A34: AP = COGS × AP% (from Assumptions)
A35: Retained Earnings = Previous + Net Income

Sheet Cash Flow
A1: Cash Flow Statement | B1: Year 1 | C1: Year 2 | D1: Year 3 | E1: Year 4 | F1: Year 5
A3: OPERATING ACTIVITIES
A4: Net Income | B4: ='Income Statement'!B14 -> 165 | C4: ='Income Statement'!C14 -> 181.5 | D4: ='Income Statement'!D14 -> 199.65 | E4: ='Income Statement'!E14 -> 219.615 | F4: ='Income Statement'!F14 -> 241.5765
A5: Add: Depreciation | B5: =Assumptions!$B$26 -> 40 | C5: =Assumptions!$B$26 -> 40 | D5: =Assumptions!$B$26 -> 40 | E5: =Assumptions!$B$26 -> 40 | F5: =Assumptions!$B$26 -> 40
A6: (Increase)/Decrease in Accounts Receivable | B6: =-('Balance Sheet'!C5-'Balance Sheet'!B5) -> -88 | C6: =-('Balance Sheet'!D5-'Balance Sheet'!C5) -> -8.8 | D6: =-('Balance Sheet'!E5-'Balance Sheet'!D5) -> -9.68 | E6: =-('Balance Sheet'!F5-'Balance Sheet'!E5) -> -10.648 | F6: =-('Balance Sheet'!G5-'Balance Sheet'!F5) -> -11.7128
A7: (Increase)/Decrease in Inventory | B7: =-('Balance Sheet'!C6-'Balance Sheet'!B6) -> -99 | C7: =-('Balance Sheet'!D6-'Balance Sheet'!C6) -> -9.9 | D7: =-('Balance Sheet'!E6-'Balance Sheet'!D6) -> -10.89 | E7: =-('Balance Sheet'!F6-'Balance Sheet'!E6) -> -11.979 | F7: =-('Balance Sheet'!G6-'Balance Sheet'!F6) -> -13.1769
A8: Increase/(Decrease) in Accounts Payable | B8: ='Balance Sheet'!C16-'Balance Sheet'!B16 -> 52.8 | C8: ='Balance Sheet'!D16-'Balance Sheet'!C16 -> 5.28 | D8: ='Balance Sheet'!E16-'Balance Sheet'!D16 -> 5.808 | E8: ='Balance Sheet'!F16-'Balance Sheet'!E16 -> 6.3888 | F8: ='Balance Sheet'!G16-'Balance Sheet'!F16 -> 7.02768
A9: Cash from Operations | B9: =B4+B5+B6+B7+B8 -> 70.8 | C9: =C4+C5+C6+C7+C8 -> 208.08 | D9: =D4+D5+D6+D7+D8 -> 224.888 | E9: =E4+E5+E6+E7+E8 -> 243.3768 | F9: =F4+F5+F6+F7+F8 -> 263.71448
A11: INVESTING ACTIVITIES
A12: Capital Expenditures (Capex) | B12: =-Assumptions!$B$25 -> -50 | C12: =-Assumptions!$B$25 -> -50 | D12: =-Assumptions!$B$25 -> -50 | E12: =-Assumptions!$B$25 -> -50 | F12: =-Assumptions!$B$25 -> -50
A13: Cash from Investing | B13: =B12 -> -50 | C13: =C12 -> -50 | D13: =D12 -> -50 | E13: =E12 -> -50 | F13: =F12 -> -50
A15: FINANCING ACTIVITIES
A16: Change in Short-Term Debt | B16: ='Balance Sheet'!C17-'Balance Sheet'!B17 -> 0 | C16: ='Balance Sheet'!D17-'Balance Sheet'!C17 -> 0 | D16: ='Balance Sheet'!E17-'Balance Sheet'!D17 -> 0 | E16: ='Balance Sheet'!F17-'Balance Sheet'!E17 -> 0 | F16: ='Balance Sheet'!G17-'Balance Sheet'!F17 -> 0
A17: Change in Long-Term Debt | B17: ='Balance Sheet'!C20-'Balance Sheet'!B20 -> 0 | C17: ='Balance Sheet'!D20-'Balance Sheet'!C20 -> 0 | D17: ='Balance Sheet'!E20-'Balance Sheet'!D20 -> 0 | E17: ='Balance Sheet'!F20-'Balance Sheet'!E20 -> 0 | F17: ='Balance Sheet'!G20-'Balance Sheet'!F20 -> 0
A18: Cash from Financing | B18: =B16+B17 -> 0 | C18: =C16+C17 -> 0 | D18: =D16+D17 -> 0 | E18: =E16+E17 -> 0 | F18: =F16+F17 -> 0
A20: Net Change in Cash | B20: =B9+B13+B18 -> 20.8 | C20: =C9+C13+C18 -> 158.08 | D20: =D9+D13+D18 -> 174.888 | E20: =E9+E13+E18 -> 193.3768 | F20: =F9+F13+F18 -> 213.71448
A21: Beginning Cash | B21: ='Balance Sheet'!B4 -> 100 | C21: ='Balance Sheet'!C4 -> 120.8 | D21: ='Balance Sheet'!D4 -> 278.88 | E21: ='Balance Sheet'!E4 -> 453.768 | F21: ='Balance Sheet'!F4 -> 647.1448
A22: Ending Cash | B22: =B21+B20 -> 120.8 | C22: =C21+C20 -> 278.88 | D22: =D21+D20 -> 453.768 | E22: =E21+E20 -> 647.1448 | F22: =F21+F20 -> 860.85928

Sheet DCF Valuation
A1: DCF Valuation | B1: Year 1 | C1: Year 2 | D1: Year 3 | E1: Year 4 | F1: Year 5
A3: Free Cash Flow Calculation
A4: Operating Income (EBIT) | B4: ='Income Statement'!B8 -> 220 | C4: ='Income Statement'!C8 -> 242 | D4: ='Income Statement'!D8 -> 266.2 | E4: ='Income Statement'!E8 -> 292.82 | F4: ='Income Statement'!F8 -> 322.102
A5: Less: Taxes | B5: =B4*Assumptions!$F$12 -> 55 | C5: =C4*Assumptions!$B$12 -> 60.5 | D5: =D4*Assumptions!$B$12 -> 66.55 | E5: =E4*Assumptions!$B$12 -> 73.205 | F5: =F4*Assumptions!$B$12 -> 80.5255
A6: EBIAT (EBIT After Tax) | B6: =B4-B5 -> 165 | C6: =C4-C5 -> 181.5 | D6: =D4-D5 -> 199.65 | E6: =E4-E5 -> 219.615 | F6: =F4-F5 -> 241.5765
A7: Add: Depreciation | B7: =Assumptions!$B$26 -> 40 | C7: =Assumptions!$B$26 -> 40 | D7: =Assumptions!$B$26 -> 40 | E7: =Assumptions!$B$26 -> 40 | F7: =Assumptions!$B$26 -> 40
A8: Less: Capex | B8: =-Assumptions!$B$25 -> -50 | C8: =-Assumptions!$B$25 -> -50 | D8: =-Assumptions!$B$25 -> -50 | E8: =-Assumptions!$B$25 -> -50 | F8: =-Assumptions!$B$25 -> -50
A9: Less: Change in Working Capital | B9: =-(('Balance Sheet'!C5-'Balance Sheet'!B5)+('Balance Sheet'!C6-'Balance Sheet'!B6)-('Balance Sheet'!C16-'Balance Sheet'!B16)) -> -134.2 | C9: =-(('Balance Sheet'!D5-'Balance Sheet'!C5)+('Balance Sheet'!D6-'Balance Sheet'!C6)-('Balance Sheet'!D16-'Balance Sheet'!C16)) -> -13.42 | D9: =-(('Balance Sheet'!E5-'Balance Sheet'!D5)+('Balance Sheet'!E6-'Balance Sheet'!D6)-('Balance Sheet'!E16-'Balance Sheet'!D16)) -> -14.762 | E9: =-(('Balance Sheet'!F5-'Balance Sheet'!E5)+('Balance Sheet'!F6-'Balance Sheet'!E6)-('Balance Sheet'!F16-'Balance Sheet'!E16)) -> -16.2382 | F9: =-(('Balance Sheet'!G5-'Balance Sheet'!F5)+('Balance Sheet'!G6-'Balance Sheet'!F6)-('Balance Sheet'!G16-'Balance Sheet'!F16)) -> -17.86202
A10: Free Cash Flow (FCF) | B10: =B6+B7+B8+B9 -> 20.8 | C10: =C6+C7+C8+C9 -> 158.08 | D10: =D6+D7+D8+D9 -> 174.888 | E10: =E6+E7+E8+E9 -> 193.3768 | F10: =F6+F7+F8+F9 -> 213.71448
A12: Discounting
A13: Discount Rate (WACC) | B13: =Assumptions!$F$15 -> 0.1 | C13: =Assumptions!$F$15 -> 0.1 | D13: =Assumptions!$F$15 -> 0.1 | E13: =Assumptions!$F$15 -> 0.1 | F13: =Assumptions!$F$15 -> 0.1
A14: Discount Period | B14: 1 | C14: 2 | D14: 3 | E14: 4 | F14: 5
A15: Discount Factor | B15: =1/(1+B13)^B14 -> 0.90909091 | C15: =1/(1+C13)^C14 -> 0.82644628 | D15: =1/(1+D13)^D14 -> 0.7513148 | E15: =1/(1+E13)^E14 -> 0.68301346 | F15: =1/(1+F13)^F14 -> 0.62092132
A16: Present Value of FCF | B16: =B10*B15 -> 18.909091 | C16: =C10*C15 -> 130.64463 | D16: =D10*D15 -> 131.39594 | E16: =E10*E15 -> 132.07896 | F16: =F10*F15 -> 132.69988
A18: Terminal Value
A19: Terminal Growth Rate | B19: =Assumptions!$F$16 -> 0.03
A20: Terminal Value | B20: =F10*(1+$B$19)/($B$13-$B$19) -> 3144.6559
A21: PV of Terminal Value | B21: =B20*F15 -> 1952.5839
A23: Valuation Summary
A24: Sum of PV of FCFs | B24: =SUM($B$16:$F$16) -> 545.7285
A25: PV of Terminal Value | B25: =$B$21 -> 1952.5839
A26: Enterprise Value | B26: =B24+B25 -> 2498.3124
A27: Less: Debt | B27: =-('Balance Sheet'!$G$17+'Balance Sheet'!$G$20) -> -250
A28: Add: Cash | B28: ='Balance Sheet'!$G$4 -> 860.85928
A29: Equity Value | B29: =B26+B27+B28 -> 3109.1717

Sheet Ratios
A1: Financial Ratios | B1: Year 1 | C1: Year 2 | D1: Year 3 | E1: Year 4 | F1: Year 5
A3: Profitability Ratios
A4: Gross Margin | B4: ='Income Statement'!B5/'Income Statement'!B3 -> 0.4 | C4: ='Income Statement'!C5/'Income Statement'!C3 -> 0.4 | D4: ='Income Statement'!D5/'Income Statement'!D3 -> 0.4 | E4: ='Income Statement'!E5/'Income Statement'!E3 -> 0.4 | F4: ='Income Statement'!F5/'Income Statement'!F3 -> 0.4
A5: Operating Margin | B5: ='Income Statement'!B8/'Income Statement'!B3 -> 0.2 | C5: ='Income Statement'!C8/'Income Statement'!C3 -> 0.2 | D5: ='Income Statement'!D8/'Income Statement'!D3 -> 0.2 | E5: ='Income Statement'!E8/'Income Statement'!E3 -> 0.2 | F5: ='Income Statement'!F8/'Income Statement'!F3 -> 0.2
A6: Net Profit Margin | B6: ='Income Statement'!B14/'Income Statement'!B3 -> 0.15 | C6: ='Income Statement'!C14/'Income Statement'!C3 -> 0.15 | D6: ='Income Statement'!D14/'Income Statement'!D3 -> 0.15 | E6: ='Income Statement'!E14/'Income Statement'!E3 -> 0.15 | F6: ='Income Statement'!F14/'Income Statement'!F3 -> 0.15
A8: Liquidity Ratios
A9: Current Ratio | B9: ='Balance Sheet'!C7/'Balance Sheet'!C18 -> 2.9941634 | C9: ='Balance Sheet'!D7/'Balance Sheet'!D18 -> 4.4835307 | D9: ='Balance Sheet'!E7/'Balance Sheet'!E18 -> 5.971112 | E9: ='Balance Sheet'!F7/'Balance Sheet'!F18 -> 7.4498307 | F9: ='Balance Sheet'!G7/'Balance Sheet'!G18 -> 8.9128519
A11: Leverage Ratios
A12: Debt-to-Equity | B12: =('Balance Sheet'!C17+'Balance Sheet'!C20)/'Balance Sheet'!C25 -> 0.48543689 | C12: =('Balance Sheet'!D17+'Balance Sheet'!D20)/'Balance Sheet'!D25 -> 0.35893754 | D12: =('Balance Sheet'!E17+'Balance Sheet'!E20)/'Balance Sheet'!E25 -> 0.27897115 | E12: =('Balance Sheet'!F17+'Balance Sheet'!F20)/'Balance Sheet'!F25 -> 0.22406152 | F12: =('Balance Sheet'!G17+'Balance Sheet'!G20)/'Balance Sheet'!G25 -> 0.18418357
A13: Debt-to-Assets | B13: =('Balance Sheet'!C17+'Balance Sheet'!C20)/'Balance Sheet'!C13 -> 0.30569821 | C13: =('Balance Sheet'!D17+'Balance Sheet'!D20)/'Balance Sheet'!D13 -> 0.24886022 | D13: =('Balance Sheet'!E17+'Balance Sheet'!E20)/'Balance Sheet'!E13 -> 0.20660508 | E13: =('Balance Sheet'!F17+'Balance Sheet'!F20)/'Balance Sheet'!F13 -> 0.17408964 | F13: =('Balance Sheet'!G17+'Balance Sheet'!G20)/'Balance Sheet'!G13 -> 0.14839913
A15: Return Ratios
A16: Return on Assets (ROA) | B16: ='Income Statement'!B14/'Balance Sheet'!C13 -> 0.20176082 | C16: ='Income Statement'!C14/'Balance Sheet'!D13 -> 0.18067252 | D16: ='Income Statement'!D14/'Balance Sheet'!E13 -> 0.16499482 | E16: ='Income Statement'!E14/'Balance Sheet'!F13 -> 0.15293079 | F16: ='Income Statement'!F14/'Balance Sheet'!G13 -> 0.14339897
A17: Return on Equity (ROE) | B17: ='Income Statement'!B14/'Balance Sheet'!C25 -> 0.32038835 | C17: ='Income Statement'!C14/'Balance Sheet'!D25 -> 0.26058866 | D17: ='Income Statement'!D14/'Balance Sheet'!E25 -> 0.22278636 | E17: ='Income Statement'!E14/'Balance Sheet'!F25 -> 0.19682908 | F17: ='Income Statement'!F14/'Balance Sheet'!G25 -> 0.17797769

Sheet Scenarios
A1: Scenario Analysis
A3: Select Scenario: | B3: Base Case | C3: Bull Case | D3: Bear Case
A5: Key Assumptions
A6: Revenue Growth Rate | B6: =Assumptions!B7 -> 0.1 | C6: =Assumptions!C7 -> 0.15 | D6: =Assumptions!D7 -> 0.05
A7: COGS (% of Revenue) | B7: =Assumptions!B10 -> 0.6 | C7: =Assumptions!C10 -> 0.55 | D7: =Assumptions!D10 -> 0.65
A8: Operating Expenses (% of Revenue) | B8: =Assumptions!B11 -> 0.2 | C8: =Assumptions!C11 -> 0.18 | D8: =Assumptions!D11 -> 0.23
A9: Discount Rate (WACC) | B9: =Assumptions!B15 -> 0.1 | C9: =Assumptions!C15 -> 0.08 | D9: =Assumptions!D15 -> 0.12
A10: Terminal Growth Rate | B10: =Assumptions!B16 -> 0.03 | C10: =Assumptions!C16 -> 0.04 | D10: =Assumptions!D16 -> 0.02
A12: Valuation Output
A13: Year 5 Revenue | B13: ='Income Statement'!$F$3 -> 1610.51 | C13: ='Income Statement'!$F$3 -> 1610.51 | D13: ='Income Statement'!$F$3 -> 1610.51
A14: Year 5 Net Income | B14: ='Income Statement'!$F$14 -> 241.5765 | C14: ='Income Statement'!$F$14 -> 241.5765 | D14: ='Income Statement'!$F$14 -> 241.5765
A15: Enterprise Value | B15: ='DCF Valuation'!$B$26 -> 2498.3124 | C15: ='DCF Valuation'!$B$26 -> 2498.3124 | D15: ='DCF Valuation'!$B$26 -> 2498.3124
A16: Equity Value | B16: ='DCF Valuation'!$B$29 -> 3109.1717 | C16: ='DCF Valuation'!$B$29 -> 3109.1717 | D16: ='DCF Valuation'!$B$29 -> 3109.1717
